<?xml version="1.0" encoding="utf-8" ?><dwsync><file name="index.php" server="turing.acm.org//home/mhelmick/sigcse2010/" local="3343697090" remote="41999184257" /><file name="registration.php" server="turing.acm.org//home/mhelmick/sigcse2010/" local="3342126912" remote="72063955332" /><file name="bonus_activities.php" server="turing.acm.org//home/mhelmick/sigcse2010/" local="3339292961" remote="89243824505" /><file name="fees.php" server="turing.acm.org//home/mhelmick/sigcse2010/" local="3339292885" remote="37704216960" /><file name="floor_plans.php" server="turing.acm.org//home/mhelmick/sigcse2010/" local="3339293108" remote="67768988032" /><file name="kids_camp.php" server="turing.acm.org//home/mhelmick/sigcse2010/" local="3339293139" remote="59179053442" /><file name="local_attractions.php" server="turing.acm.org//home/mhelmick/sigcse2010/" local="3341893523" remote="93538791811" /><file name="pre_symposium_events.php" server="turing.acm.org//home/mhelmick/sigcse2010/" local="3343694221" remote="106423693699" /><file name="reception.php" server="turing.acm.org//home/mhelmick/sigcse2010/" local="3339287360" remote="59179053444" /><file name="special_projects.php" server="turing.acm.org//home/mhelmick/sigcse2010/" local="3339292933" remote="89243824517" /><file name="supporter_sessions.php" server="turing.acm.org//home/mhelmick/sigcse2010/" local="3344392681" remote="97833759109" /><file name="travel_information.php" server="turing.acm.org//home/mhelmick/sigcse2010/" local="3343697721" remote="97833759110" /><file name="video_program.php" server="turing.acm.org//home/mhelmick/sigcse2010/" local="3339293023" remote="76358922630" /><file name="visas.php" server="turing.acm.org//home/mhelmick/sigcse2010/" local="3343956329" remote="41999184263" /><file name="accommodations.php" server="turing.acm.org//home/mhelmick/sigcse2010/" local="3343698289" remote="80653889913" /><file name="k12_highlights.php" server="turing.acm.org//home/mhelmick/sigcse2010/" local="3343619104" remote="80653889921" /><file name="keynotes.php" server="turing.acm.org//home/mhelmick/sigcse2010/" local="3344304602" remote="54884086146" /><file name="evaluations.php" server="turing.acm.org//home/mhelmick/sigcse2010/" local="3343854985" remote="67768988031" /></dwsync>